{
  "gitSyncId": "67fc6671d8dd0e25198e9dee_d848a3c4-1266-4064-a43e-0b7246e17724",
  "id": "Tasks_utils.getCompletedTasks",
  "pluginId": "js-plugin",
  "pluginType": "JS",
  "unpublishedAction": {
    "actionConfiguration": {
      "encodeParamsToggle": true,
      "jsArguments": [],
      "paginationType": "NONE",
      "timeoutInMillisecond": 10000
    },
    "collectionId": "Tasks_utils",
    "confirmBeforeExecute": false,
    "datasource": {
      "isAutoGenerated": false,
      "name": "UNUSED_DATASOURCE",
      "pluginId": "js-plugin"
    },
    "dynamicBindingPathList": [
      {
        "key": "body"
      }
    ],
    "executeOnLoad": true,
    "fullyQualifiedName": "utils.getCompletedTasks",
    "name": "getCompletedTasks",
    "pageId": "Tasks",
    "userSetOnLoad": false
  }
}